sidrapy/__init__.py
sidrapy/table.py
sidrapy/resources/__init__.py
sidrapy/resources/handler.py
sidrapy/resources/http_client.py
sidrapy-0.1.4.dist-info/LICENSE
sidrapy-0.1.4.dist-info/METADATA
sidrapy-0.1.4.dist-info/WHEEL
sidrapy-0.1.4.dist-info/top_level.txt
sidrapy-0.1.4.dist-info/RECORD
