Metadata-Version: 2.1
Name: sidrapy
Version: 0.1.4
Summary: A library that provides a python interface for the IBGE SIDRA API.
Home-page: https://github.com/AlanTaranti/sidrapy
Maintainer: Alan Taranti
Maintainer-email: contato@alantaranti.me
License: MIT
Project-URL: Documentation, https://sidrapy.readthedocs.io
Project-URL: Code, https://github.com/AlanTaranti/sidrapy
Project-URL: Issue tracker, https://github.com/AlanTaranti/sidrapy/issues
Keywords: ibge,sidra,api,brasil,brazil,estatistica,statistics
Classifier: Development Status :: 3 - Alpha
Classifier: Intended Audience :: Developers
Classifier: Intended Audience :: Science/Research
Classifier: License :: OSI Approved :: MIT License
Classifier: Natural Language :: Portuguese (Brazilian)
Classifier: Operating System :: OS Independent
Classifier: Programming Language :: Python :: 3.7
Classifier: Programming Language :: Python :: 3.8
Classifier: Programming Language :: Python :: 3.9
Classifier: Programming Language :: Python :: 3.10
Classifier: Topic :: Scientific/Engineering
Requires-Python: >=3.7
License-File: LICENSE
